{
  "project_info": {
    "project_number": "374772074763",
    "project_id": "my-doggiedon",
    "storage_bucket": "my-doggiedon.firebasestorage.app"
  },
  "client": [
    {
      "client_info": {
        "mobilesdk_app_id": "1:374772074763:android:3b4351bf8eb61651b67a0e",
        "android_client_info": {
          "package_name": "com.example.doggiedon"
        }
      },
      "oauth_client": [
        {
          "client_id": "374772074763-u70rkd6qu38n43aldtjpcslpnmnip6ru.apps.googleusercontent.com",
          "client_type": 1,
          "android_info": {
            "package_name": "com.example.doggiedon",
            "certificate_hash": "1f01d4bcff80edd6460c86bf855841d08eba68ad"
          }
        },
        {
          "client_id": "374772074763-l3lmmij3i4844u8ep5p1skg9pktua182.apps.googleusercontent.com",
          "client_type": 3
        }
      ],
      "api_key": [
        {
          "current_key": "AIzaSyCI4ITu35BNBkFHHmP8XJBNAYZZhKuau4U"
        }
      ],
      "services": {
        "appinvite_service": {
          "other_platform_oauth_client": [
            {
              "client_id": "374772074763-l3lmmij3i4844u8ep5p1skg9pktua182.apps.googleusercontent.com",
              "client_type": 3
            }
          ]
        }
      }
    }
  ],
  "configuration_version": "1"
}